MANIFEST.in
README.txt
setup.py
badeeshello/__init__.py
badeeshello/hello.py
badeeshello.egg-info/PKG-INFO
badeeshello.egg-info/SOURCES.txt
badeeshello.egg-info/dependency_links.txt
badeeshello.egg-info/top_level.txt
badeeshello/images/__init__.py
badeeshello/images/hello.gif