Metadata-Version: 1.0
Name: badeeshello
Version: 0.1
Summary: Hello World testing setuptools
Home-page: http://www.experian.com
Author: Badees Nouiouat
Author-email: badees98@gmail.com
License: BSD
Platform: UNKNOWN
